pytest_async_generators/__init__.py
pytest_async_generators/subscribe_to_messages.py
pytest_async_generators-0.0.4.dist-info/METADATA
pytest_async_generators-0.0.4.dist-info/WHEEL
pytest_async_generators-0.0.4.dist-info/entry_points.txt
pytest_async_generators-0.0.4.dist-info/RECORD
