Metadata-Version: 2.1
Name: pytest-async-generators
Version: 0.0.4
Summary: Pytest fixtures for async generators
Home-page: https://github.com/possibilities/pytest-async-generators
Author: Mike Bannister
Author-email: notimpossiblemike@gmail.com
Requires-Python: >=3.11,<4.0
Classifier: Programming Language :: Python :: 3
Classifier: Programming Language :: Python :: 3.11
Requires-Dist: pytest-asyncio (>=0.21.0,<0.22.0)
Project-URL: Repository, https://github.com/possibilities/pytest-async-generators
